{
    "app-id": "com.github.bvschaik.julius",
    "runtime": "org.freedesktop.Platform",
    "runtime-version": "23.08",
    "sdk": "org.freedesktop.Sdk",
    "finish-args": [
        "--filesystem=home",
        "--share=ipc",
        "--device=dri",
        "--socket=wayland",
        "--socket=fallback-x11",
        "--socket=pulseaudio"
     ],
    "command": "julius",
    "modules": [
        {
            "name": "julius",
            "buildsystem": "cmake-ninja",
            "sources": [
                {
                    "type": "archive",
                    "url": "https://github.com/bvschaik/julius/archive/v1.8.0.tar.gz",
                    "sha256": "e479e0b60074497b3e81b30749e040c423f493d469d630a774c06b3d61d91159"
                }
            ]
        }
    ]
}
